<annotation>
	<folder>1</folder>
	<filename>1_15.jpg</filename>
	<path>D:\存储\BaiduNetdiskDownload\fire_detection\VOC2020\1\1_15.jpg</path>
	<source>
		<database>Unknown</database>
	</source>
	<size>
		<width>960</width>
		<height>540</height>
		<depth>3</depth>
	</size>
	<segmented>0</segmented>
	<object>
		<name>fire</name>
		<pose>Unspecified</pose>
		<truncated>0</truncated>
		<difficult>0</difficult>
		<bndbox>
			<xmin>771</xmin>
			<ymin>248</ymin>
			<xmax>799</xmax>
			<ymax>302</ymax>
		</bndbox>
	</object>
	<object>
		<name>fire</name>
		<pose>Unspecified</pose>
		<truncated>0</truncated>
		<difficult>0</difficult>
		<bndbox>
			<xmin>366</xmin>
			<ymin>353</ymin>
			<xmax>484</xmax>
			<ymax>394</ymax>
		</bndbox>
	</object>
</annotation>
